site24x7_openai_observability/__init__.py
site24x7_openai_observability/config.py
site24x7_openai_observability/constants.py
site24x7_openai_observability/instrumentation.py
site24x7_openai_observability/logger.py
site24x7_openai_observability/tracker.py
site24x7_openai_observability/util.py
site24x7_openai_observability/instrumentation/__init__.py
site24x7_openai_observability/instrumentation/instrument.py
site24x7_openai_observability/instrumentation/patch.py
site24x7_openai_observability/instrumentation/util.py
site24x7_openai_observability/instrumentation/openai/__init__.py
site24x7_openai_observability/instrumentation/openai/instrument.py
site24x7_openai_observability/instrumentation/openai/wrapper.py
site24x7_openai_observability/instrumentation/packages/__init__.py
site24x7_openai_observability/instrumentation/packages/openai.py
site24x7_openai_observability/instrumentation/packages/openai_old.py
site24x7_openai_observability-1.1.0.dist-info/LICENSE.txt
site24x7_openai_observability-1.1.0.dist-info/METADATA
site24x7_openai_observability-1.1.0.dist-info/WHEEL
site24x7_openai_observability-1.1.0.dist-info/top_level.txt
site24x7_openai_observability-1.1.0.dist-info/RECORD
