Metadata-Version: 2.1
Name: site24x7_openai_observability
Version: 1.1.0
Summary: Tool to monitor openai requests
Home-page: https://site24x7.com
Author: Zoho Corporation Pvt. Ltd.
Author-email: apm-insight@zohocorp.com
License: LICENSE.txt
Requires-Python: >=3.5
License-File: LICENSE.txt
Requires-Dist: requests
